AUTHORS.rst
CONTRIBUTING.rst
HISTORY.rst
LICENSE
MANIFEST.in
README.rst
requirements.txt
setup.cfg
setup.py
test_requirements.txt
cisco_zeus.egg-info/PKG-INFO
cisco_zeus.egg-info/SOURCES.txt
cisco_zeus.egg-info/dependency_links.txt
cisco_zeus.egg-info/not-zip-safe
cisco_zeus.egg-info/requires.txt
cisco_zeus.egg-info/top_level.txt
docs/Makefile
docs/authors.rst
docs/conf.py
docs/contributing.rst
docs/history.rst
docs/index.rst
docs/installation.rst
docs/make.bat
docs/modules.rst
docs/readme.rst
docs/usage.rst
docs/zeus.rst
tests/.test_zeus_client.py.un~
tests/__init__.py
tests/test_zeus_client.py
zeus/__init__.py
zeus/client.py
zeus/interfaces/__init__.py
zeus/interfaces/alerts.py
zeus/interfaces/logs.py
zeus/interfaces/metrics.py
zeus/interfaces/rest.py
zeus/interfaces/trigalerts.py
zeus/interfaces/utils.py