Metadata-Version: 1.1
Name: cisco-zeus
Version: 0.2.2.6
Summary: Python client for CiscoZeus.io. It allows a user to post/query logs and metrics using Zeus.
Home-page: https://github.com/CiscoZeus/python-zeusclient.git
Author: Marc Solanas Tarre
Author-email: msolanas@cisco.com
License: Apache License 2.0
Keywords: zeus
Platform: UNKNOWN
Classifier: Development Status :: 3 - Alpha
Classifier: Intended Audience :: Developers
Classifier: License :: OSI Approved :: Apache Software License
Classifier: Natural Language :: English
Classifier: Programming Language :: Python :: 2
Classifier: Programming Language :: Python :: 2.6
Classifier: Programming Language :: Python :: 2.7
